{
    "diagram_id": "2EBT9X85P2WH9FYUD9UJ",
    "image_filename": "2EBT9X85P2WH9FYUD9UJ.jpg",
    "make": "ferrari",
    "hotspots": [
        {
            "id": "10",
            "label": "10",
            "position": {
                "x": "0.375903",
                "y": "0.986743"
            },
            "parts": [
                "14059290"
            ]
        },
        {
            "id": "12",
            "label": "12",
            "position": {
                "x": "0.271071",
                "y": "0.65569"
            },
            "parts": [
                "144443"
            ]
        },
        {
            "id": "5",
            "label": "5",
            "position": {
                "x": "0.273695",
                "y": "0.491037"
            },
            "parts": [
                "14059421"
            ]
        },
        {
            "id": "8",
            "label": "8",
            "position": {
                "x": "0.273823",
                "y": "0.717901"
            },
            "parts": [
                "238988"
            ]
        },
        {
            "id": "10",
            "label": "10",
            "position": {
                "x": "0.952182",
                "y": "0.681562"
            },
            "parts": [
                "14059290"
            ]
        },
        {
            "id": "11",
            "label": "11",
            "position": {
                "x": "0.951591",
                "y": "0.638974"
            },
            "parts": [
                "12643724"
            ]
        },
        {
            "id": "5",
            "label": "5",
            "position": {
                "x": "0.715261",
                "y": "0.311801"
            },
            "parts": [
                "14059421"
            ]
        },
        {
            "id": "12",
            "label": "12",
            "position": {
                "x": "0.888839",
                "y": "0.360681"
            },
            "parts": [
                "144443"
            ]
        },
        {
            "id": "3",
            "label": "3",
            "position": {
                "x": "0.634154",
                "y": "0.317074"
            },
            "parts": [
                "12648978"
            ]
        },
        {
            "id": "4",
            "label": "4",
            "position": {
                "x": "0.274293",
                "y": "0.592874"
            },
            "parts": [
                "255108"
            ]
        },
        {
            "id": "6",
            "label": "6",
            "position": {
                "x": "0.274067",
                "y": "0.780881"
            },
            "parts": [
                "80209900"
            ]
        },
        {
            "id": "2",
            "label": "2",
            "position": {
                "x": "0.273661",
                "y": "0.367893"
            },
            "parts": [
                "10902380"
            ]
        },
        {
            "id": "3",
            "label": "3",
            "position": {
                "x": "0.273925",
                "y": "0.333623"
            },
            "parts": [
                "12648978"
            ]
        },
        {
            "id": "11",
            "label": "11",
            "position": {
                "x": "0.375274",
                "y": "0.940592"
            },
            "parts": [
                "12643724"
            ]
        },
        {
            "id": "9",
            "label": "9",
            "position": {
                "x": "0.566729",
                "y": "0.987138"
            },
            "parts": [
                "238988"
            ]
        },
        {
            "id": "1",
            "label": "1",
            "position": {
                "x": "0.273683",
                "y": "0.401549"
            },
            "parts": [
                "69248100"
            ]
        },
        {
            "id": "7",
            "label": "7",
            "position": {
                "x": "0.951253",
                "y": "0.595125"
            },
            "parts": [
                "80210000"
            ]
        }
    ]
}